groupeffect/__init__.py
groupeffect/framework.py
groupeffect-0.1.0.dist-info/LICENSE
groupeffect-0.1.0.dist-info/METADATA
groupeffect-0.1.0.dist-info/WHEEL
groupeffect-0.1.0.dist-info/top_level.txt
groupeffect-0.1.0.dist-info/RECORD
