Metadata-Version: 2.1
Name: groupeffect
Version: 0.1.0
Summary: reusable scripts for development
Author: Amir Yousefi
Project-URL: Homepage, https://github.com/Groupeffect
Classifier: Programming Language :: Python :: 3
Classifier: License :: OSI Approved :: MIT License
Classifier: Operating System :: OS Independent
Requires-Python: >=3.10
License-File: LICENSE
